{
  "week": 17,
  "season": 2025,
  "generated": "2025-12-24T20:25:40.283660+00:00",
  "games": [
    {
      "gameId": "401772710",
      "dateTime": "2025-12-25T18:00:00+00:00",
      "awayTeam": "DAL",
      "homeTeam": "WAS",
      "vegasSpread": 8.5,
      "vegasTotal": 50.5,
      "prediction": 4.803495816190443,
      "spreadDiff": 3.696504183809557,
      "betRecommendation": "WAS",
      "awayRecord": "6-8-1",
      "homeRecord": null
    },
    {
      "gameId": "401772711",
      "dateTime": "2025-12-25T21:30:00+00:00",
      "awayTeam": "DET",
      "homeTeam": "MIN",
      "vegasSpread": 7.5,
      "vegasTotal": 43.5,
      "prediction": 5.485344706127081,
      "spreadDiff": 2.014655293872919,
      "betRecommendation": "MIN",
      "awayRecord": "8-7",
      "homeRecord": "7-8"
    },
    {
      "gameId": "401772622",
      "dateTime": "2025-12-26T01:15:00+00:00",
      "awayTeam": "DEN",
      "homeTeam": "KC",
      "vegasSpread": 13.5,
      "vegasTotal": 36.5,
      "prediction": 3.4134927092318175,
      "spreadDiff": 10.086507290768182,
      "betRecommendation": "KC",
      "awayRecord": "12-3",
      "homeRecord": "6-9"
    },
    {
      "gameId": "401772951",
      "dateTime": "2025-12-27T21:30:00+00:00",
      "awayTeam": "HOU",
      "homeTeam": "LAC",
      "vegasSpread": -1.5,
      "vegasTotal": 39.5,
      "prediction": -0.7160656725646989,
      "spreadDiff": 0.7839343274353011,
      "betRecommendation": "HOU",
      "awayRecord": "10-5",
      "homeRecord": "11-4"
    },
    {
      "gameId": "401772953",
      "dateTime": "2025-12-28T01:00:00+00:00",
      "awayTeam": "BAL",
      "homeTeam": "GB",
      "vegasSpread": -3.0,
      "vegasTotal": 40.5,
      "prediction": -2.430766780280294,
      "spreadDiff": 0.5692332197197061,
      "betRecommendation": "BAL",
      "awayRecord": "7-8",
      "homeRecord": "9-5-1"
    },
    {
      "gameId": "401772954",
      "dateTime": "2025-12-28T18:00:00+00:00",
      "awayTeam": "ARI",
      "homeTeam": "CIN",
      "vegasSpread": -7.5,
      "vegasTotal": 52.5,
      "prediction": -6.9852843996747565,
      "spreadDiff": 0.5147156003252435,
      "betRecommendation": "ARI",
      "awayRecord": "3-12",
      "homeRecord": "5-10"
    },
    {
      "gameId": "401772807",
      "dateTime": "2025-12-28T18:00:00+00:00",
      "awayTeam": "PIT",
      "homeTeam": "CLE",
      "vegasSpread": 3.0,
      "vegasTotal": 34.5,
      "prediction": -0.3247076890495768,
      "spreadDiff": 3.3247076890495766,
      "betRecommendation": "CLE",
      "awayRecord": "9-6",
      "homeRecord": "3-12"
    },
    {
      "gameId": "401772809",
      "dateTime": "2025-12-28T18:00:00+00:00",
      "awayTeam": "NO",
      "homeTeam": "TEN",
      "vegasSpread": 2.5,
      "vegasTotal": 39.5,
      "prediction": 0.25417874779360344,
      "spreadDiff": 2.2458212522063965,
      "betRecommendation": "TEN",
      "awayRecord": "5-10",
      "homeRecord": "3-12"
    },
    {
      "gameId": "401772915",
      "dateTime": "2025-12-28T18:00:00+00:00",
      "awayTeam": "JAX",
      "homeTeam": "IND",
      "vegasSpread": 6.5,
      "vegasTotal": 48.5,
      "prediction": 5.505205983249026,
      "spreadDiff": 0.9947940167509737,
      "betRecommendation": "IND",
      "awayRecord": "11-4",
      "homeRecord": "8-7"
    },
    {
      "gameId": "401772916",
      "dateTime": "2025-12-28T18:00:00+00:00",
      "awayTeam": "TB",
      "homeTeam": "MIA",
      "vegasSpread": 5.5,
      "vegasTotal": 45.5,
      "prediction": 5.510445779210941,
      "spreadDiff": 0.01044577921094092,
      "betRecommendation": "TB",
      "awayRecord": "7-8",
      "homeRecord": "6-9"
    },
    {
      "gameId": "401772808",
      "dateTime": "2025-12-28T18:00:00+00:00",
      "awayTeam": "NE",
      "homeTeam": "NYJ",
      "vegasSpread": 13.5,
      "vegasTotal": 42.5,
      "prediction": 1.5655612068305127,
      "spreadDiff": 11.934438793169488,
      "betRecommendation": "NYJ",
      "awayRecord": "12-3",
      "homeRecord": "3-12"
    },
    {
      "gameId": "401772952",
      "dateTime": "2025-12-28T18:00:00+00:00",
      "awayTeam": "SEA",
      "homeTeam": "CAR",
      "vegasSpread": 7.0,
      "vegasTotal": 42.5,
      "prediction": 5.574696399443322,
      "spreadDiff": 1.4253036005566777,
      "betRecommendation": "CAR",
      "awayRecord": "12-3",
      "homeRecord": "8-7"
    },
    {
      "gameId": "401772950",
      "dateTime": "2025-12-28T21:05:00+00:00",
      "awayTeam": "NYG",
      "homeTeam": "LV",
      "vegasSpread": 1.5,
      "vegasTotal": 41.5,
      "prediction": -0.2173382822114088,
      "spreadDiff": 1.7173382822114087,
      "betRecommendation": "LV",
      "awayRecord": "2-13",
      "homeRecord": "2-13"
    },
    {
      "gameId": "401772917",
      "dateTime": "2025-12-28T21:25:00+00:00",
      "awayTeam": "PHI",
      "homeTeam": "BUF",
      "vegasSpread": -1.5,
      "vegasTotal": 43.5,
      "prediction": -1.0875457712929022,
      "spreadDiff": 0.4124542287070978,
      "betRecommendation": "PHI",
      "awayRecord": "10-5",
      "homeRecord": "11-4"
    },
    {
      "gameId": "401772935",
      "dateTime": "2025-12-29T01:20:00+00:00",
      "awayTeam": "CHI",
      "homeTeam": "SF",
      "vegasSpread": -3.0,
      "vegasTotal": 52.5,
      "prediction": -3.6963972967025653,
      "spreadDiff": 0.6963972967025653,
      "betRecommendation": "SF",
      "awayRecord": "11-4",
      "homeRecord": "11-4"
    },
    {
      "gameId": "401772825",
      "dateTime": "2025-12-30T01:15:00+00:00",
      "awayTeam": "LAR",
      "homeTeam": "ATL",
      "vegasSpread": 7.5,
      "vegasTotal": 49.5,
      "prediction": 5.6916052333004465,
      "spreadDiff": 1.8083947666995535,
      "betRecommendation": "ATL",
      "awayRecord": "11-4",
      "homeRecord": "6-9"
    }
  ]
}